coptr/__init__.py
coptr/bam_processor.py
coptr/cli.py
coptr/compute_read_counts.py
coptr/compute_rel_abun.py
coptr/coptr_contig.py
coptr/coptr_ref.py
coptr/poisson_pca.py
coptr/read_assigner.py
coptr/read_mapper.py
coptr/util.py
coptr-1.1.4.dist-info/COPYING
coptr-1.1.4.dist-info/METADATA
coptr-1.1.4.dist-info/WHEEL
coptr-1.1.4.dist-info/entry_points.txt
coptr-1.1.4.dist-info/top_level.txt
coptr-1.1.4.dist-info/zip-safe
coptr-1.1.4.dist-info/RECORD
